context_server/__init__.py
context_server/main.py
local_context_server-0.1.6.dist-info/METADATA
local_context_server-0.1.6.dist-info/WHEEL
local_context_server-0.1.6.dist-info/entry_points.txt
local_context_server-0.1.6.dist-info/top_level.txt
local_context_server-0.1.6.dist-info/RECORD
